{
  "loadData": [
    {
      "AUTHOR_ID": 1,
      "DESCRIPTION": "voluptatum",
      "TITLE": "temporibus",
      "INSERTED_DATE": "2015-11-18",
      "ID": 1,
      "CONTENT": "Fugit non et doloribus repudiandae."
    },
    {
      "AUTHOR_ID": 2,
      "DESCRIPTION": "aut",
      "TITLE": "ea",
      "INSERTED_DATE": "1975-06-08",
      "ID": 2,
      "CONTENT": "Tempora molestias maiores provident molestiae sint possimus quasi."
    },
    {
      "AUTHOR_ID": 3,
      "DESCRIPTION": "rerum",
      "TITLE": "illum",
      "INSERTED_DATE": "1975-02-25",
      "ID": 3,
      "CONTENT": "Delectus recusandae sit officiis dolor."
    },
    {
      "AUTHOR_ID": 4,
      "DESCRIPTION": "deleniti",
      "TITLE": "itaque",
      "INSERTED_DATE": "2010-07-28",
      "ID": 4,
      "CONTENT": "Magni nam optio id recusandae."
    },
    {
      "AUTHOR_ID": 5,
      "DESCRIPTION": "similique",
      "TITLE": "ad",
      "INSERTED_DATE": "2006-10-09",
      "ID": 5,
      "CONTENT": "Rerum tempore quis ut nesciunt qui excepturi est."
    },
    {
      "AUTHOR_ID": 1,
      "DESCRIPTION": "test1@example.com",
      "TITLE": "Title1",
      "INSERTED_DATE": "2000-01-01",
      "ID": 6,
      "CONTENT": "Content1"
    },
    {
      "AUTHOR_ID": 2,
      "DESCRIPTION": "test2@example.com",
      "TITLE": "Title2",
      "INSERTED_DATE": "2000-01-01",
      "ID": 7,
      "CONTENT": "Content2"
    },
    {
      "AUTHOR_ID": 3,
      "DESCRIPTION": "test3@example.com",
      "TITLE": "Title3",
      "INSERTED_DATE": "2000-01-01",
      "ID": 8,
      "CONTENT": "Content3"
    }
  ]
}